keynet_train/__init__.py
keynet_train/py.typed
keynet_train/cli/__init__.py
keynet_train/cli/main.py
keynet_train/cli/validator.py
keynet_train/cli/commands/__init__.py
keynet_train/cli/commands/push.py
keynet_train/cli/config/__init__.py
keynet_train/cli/config/manager.py
keynet_train/cli/parser/__init__.py
keynet_train/cli/parser/argparse_parser.py
keynet_train/cli/parser/click_parser.py
keynet_train/cli/parser/decorator.py
keynet_train/cli/parser/extractor.py
keynet_train/cli/parser/typer_parser.py
keynet_train/clients/__init__.py
keynet_train/clients/backend.py
keynet_train/clients/base.py
keynet_train/clients/converters.py
keynet_train/clients/docker.py
keynet_train/clients/models.py
keynet_train/clients/onnx.py
keynet_train/clients/torch.py
keynet_train/config/__init__.py
keynet_train/config/settings.py
keynet_train/decorators/__init__.py
keynet_train/decorators/onnx.py
keynet_train/decorators/pytorch.py
keynet_train/utils/__init__.py
keynet_train/utils/experiment.py
keynet_train/utils/paths.py
keynet_train/utils/triton.py
keynet_train-0.8.5.dist-info/METADATA
keynet_train-0.8.5.dist-info/WHEEL
keynet_train-0.8.5.dist-info/entry_points.txt
keynet_train-0.8.5.dist-info/RECORD
