Metadata-Version: 2.4
Name: keynet-train
Version: 0.8.5
Summary: Training utilities for keynet - MLflow and model training support
Project-URL: Homepage, https://github.com/WIM-Corporation/keynet
Project-URL: Bug Tracker, https://github.com/WIM-Corporation/keynet/issues
Author-email: hbjs <hbjs97@naver.com>
License: MIT
Keywords: keynet,machine-learning,mlflow,training
Classifier: Development Status :: 3 - Alpha
Classifier: Intended Audience :: Developers
Classifier: License :: OSI Approved :: MIT License
Classifier: Programming Language :: Python :: 3
Classifier: Programming Language :: Python :: 3.9
Classifier: Programming Language :: Python :: 3.10
Classifier: Programming Language :: Python :: 3.11
Classifier: Programming Language :: Python :: 3.12
Classifier: Topic :: Scientific/Engineering :: Artificial Intelligence
Requires-Python: >=3.9
Requires-Dist: docker>=7.0.0
Requires-Dist: httpx>=0.27.0
Requires-Dist: keynet-core>=0.8.0
Requires-Dist: mlflow==3.1.1
Requires-Dist: numpy<2.0,>=1.25.0
Requires-Dist: onnx
Requires-Dist: onnxruntime<1.18.0,>=1.17.0
Requires-Dist: pika>=1.3.2
Requires-Dist: pydantic-settings>=2.0
Requires-Dist: pydantic>=2.0
Requires-Dist: questionary>=2.0.0
Requires-Dist: rich>=13.0.0
Requires-Dist: torch<=2.8
